MANIFEST.in
README.md
setup.py
txServiceRegistry/__init__.py
txServiceRegistry/client.py
txServiceRegistry.egg-info/PKG-INFO
txServiceRegistry.egg-info/SOURCES.txt
txServiceRegistry.egg-info/dependency_links.txt
txServiceRegistry.egg-info/requires.txt
txServiceRegistry.egg-info/top_level.txt
txServiceRegistry/test/__init__.py
txServiceRegistry/test/mock_http_server.py
txServiceRegistry/test/test_client.py
txServiceRegistry/test/utils.py
txServiceRegistry/utils/__init__.py
txServiceRegistry/utils/utils.py
utils/__init__.py
utils/dist.py