Metadata-Version: 1.1
Name: txServiceRegistry
Version: 0.2.0
Summary: A Twisted Python client for Rackspace Service Registry.
Home-page: https://github.com/racker/python-twisted-service-registry-client
Author: Rackspace Hosting, Inc.
Author-email: sr@rackspace.com
License: Apache License (2.0)
Platform: UNKNOWN
Classifier: Development Status :: 4 - Beta
Classifier: Programming Language :: Python :: 2.6
Classifier: Programming Language :: Python :: 2.7
Classifier: Programming Language :: Python :: Implementation :: PyPy
Classifier: Framework :: Twisted
